telelib/__init__.py
telelib/telegram.py
telelib/tools/__init__.py
telelib/tools/code_generator.py
telelib/tools/scraper.py
telelib-6.2.5.dist-info/LICENSE
telelib-6.2.5.dist-info/METADATA
telelib-6.2.5.dist-info/WHEEL
telelib-6.2.5.dist-info/top_level.txt
telelib-6.2.5.dist-info/RECORD
