Metadata-Version: 2.1
Name: telelib
Version: 6.2.5
Summary: A Telegram Wrapper Written in Python
Author: Mohammad Mahdi Afshar
Author-email: me@mamad.dev
License: The Unlicensed
Classifier: Intended Audience :: Developers
Classifier: Topic :: Software Development :: Libraries :: Python Modules
Classifier: Topic :: Communications :: Chat
Classifier: Topic :: Internet
Classifier: Programming Language :: Python
Classifier: Programming Language :: Python :: 3
Classifier: Programming Language :: Python :: 3.7
Classifier: Programming Language :: Python :: 3.8
Classifier: Programming Language :: Python :: 3.9
Classifier: Programming Language :: Python :: 3.10
Requires: thread_py
Requires: httpx
Requires: requests
Requires: coloredlogs
Requires-Python: >=3.8
License-File: LICENSE
